generated_content/__init__.py
generated_content/generator.py
generated_content/methods.py
dynamic_content_generator-0.1.0.dist-info/LICENSE
dynamic_content_generator-0.1.0.dist-info/METADATA
dynamic_content_generator-0.1.0.dist-info/WHEEL
dynamic_content_generator-0.1.0.dist-info/top_level.txt
dynamic_content_generator-0.1.0.dist-info/RECORD
